{"v":"5.7.5","fr":29.9700012207031,"ip":0,"op":90.0000036657751,"w":375,"h":812,"nm":"Splash 1.4","ddd":0,"assets":[],"layers":[{"ddd":0,"ind":1,"ty":4,"nm":"Boundary Outlines","sr":1,"ks":{"o":{"a":0,"k":100,"ix":11},"r":{"a":0,"k":0,"ix":10},"p":{"a":0,"k":[187.499,406,0],"ix":2,"l":2},"a":{"a":0,"k":[73.478,75.282,0],"ix":1,"l":2},"s":{"a":0,"k":[100,100,100],"ix":6,"l":2}},"ao":0,"sy":[{"c":{"a":0,"k":[0,0,0,1],"ix":2},"o":{"a":0,"k":75,"ix":3},"a":{"a":0,"k":120,"ix":5},"s":{"a":0,"k":5,"ix":8},"d":{"a":0,"k":5,"ix":6},"ch":{"a":0,"k":0,"ix":7},"bm":{"a":0,"k":5,"ix":1},"no":{"a":0,"k":0,"ix":9},"lc":{"a":0,"k":1,"ix":10},"ty":1,"nm":"Drop Shadow"},{"c":{"a":0,"k":[0,0,0,1],"ix":2},"o":{"a":0,"k":75,"ix":3},"a":{"a":0,"k":120,"ix":5},"s":{"a":0,"k":5,"ix":8},"d":{"a":0,"k":5,"ix":6},"ch":{"a":0,"k":0,"ix":7},"bm":{"a":0,"k":5,"ix":1},"no":{"a":0,"k":0,"ix":9},"ty":2,"nm":"Inner Shadow"},{"c":{"a":0,"k":[1,1,0.745098039216,1],"ix":5},"o":{"a":0,"k":75,"ix":2},"s":{"a":0,"k":5,"ix":10},"r":{"a":0,"k":50,"ix":11},"ch":{"a":0,"k":0,"ix":9},"bm":{"a":0,"k":11,"ix":1},"no":{"a":0,"k":0,"ix":3},"j":{"a":0,"k":0,"ix":12},"ty":3,"nm":"Outer Glow"},{"c":{"a":0,"k":[1,1,0.745098039216,1],"ix":5},"o":{"a":0,"k":75,"ix":2},"s":{"a":0,"k":5,"ix":11},"r":{"a":0,"k":50,"ix":12},"sr":{"a":0,"k":1,"ix":9},"ch":{"a":0,"k":0,"ix":10},"bm":{"a":0,"k":11,"ix":1},"no":{"a":0,"k":0,"ix":3},"j":{"a":0,"k":0,"ix":13},"ty":4,"nm":"Inner Glow"},{"bs":{"a":0,"k":2,"ix":1},"bt":{"a":0,"k":1,"ix":2},"sr":{"a":0,"k":100,"ix":3},"bd":{"a":0,"k":1,"ix":4},"s":{"a":0,"k":5,"ix":5},"so":{"a":0,"k":75,"ix":15},"ga":{"a":0,"k":0,"ix":7},"a":{"a":0,"k":120,"ix":8},"ll":{"a":0,"k":30,"ix":9},"hm":{"a":0,"k":11,"ix":10},"hc":{"a":0,"k":[1,1,1,1],"ix":11},"ho":{"a":0,"k":75,"ix":12},"sm":{"a":0,"k":5,"ix":13},"sc":{"a":0,"k":[0,0,0,1],"ix":14},"ty":5,"nm":"Bevel and Emboss"},{"bm":{"a":0,"k":5,"ix":1},"c":{"a":0,"k":[0,0,0,1],"ix":2},"o":{"a":0,"k":50,"ix":3},"a":{"a":0,"k":19,"ix":4},"d":{"a":0,"k":11,"ix":5},"s":{"a":0,"k":14,"ix":6},"in":{"a":0,"k":1,"ix":7},"ty":6,"nm":"Satin"},{"bm":{"a":0,"k":1,"ix":1},"c":{"a":0,"k":[1,0,0,1],"ix":2},"so":{"a":0,"k":100,"ix":3},"ty":7,"nm":"Color Overlay"},{"bm":{"a":0,"k":1,"ix":1},"o":{"a":0,"k":100,"ix":2},"gf":{"a":0,"ix":3},"gs":{"a":0,"k":100,"ix":4},"a":{"a":0,"k":90,"ix":5},"gt":{"a":0,"k":1,"ix":6},"re":{"a":0,"k":0,"ix":7},"al":{"a":0,"k":1,"ix":8},"s":{"a":0,"k":100,"ix":9},"of":{"a":0,"k":[0,0],"ix":10},"ty":8,"nm":"Gradient Overlay"},{"c":{"a":0,"k":[1,0,0,1],"ix":2},"s":{"a":0,"k":3,"ix":3},"ty":0,"nm":"Stroke"}],"shapes":[{"ty":"gr","it":[{"ind":0,"ty":"sh","ix":1,"ks":{"a":1,"k":[{"i":{"x":0,"y":1},"o":{"x":0.333,"y":0},"t":0,"s":[{"i":[[0,0],[0,0],[-12.881,0],[0,0],[0,-0.865],[0.865,0],[0,0],[0,-13.606],[0,0],[0.865,0],[0,0.865]],"o":[[0,0],[0,-15.62],[0,0],[0.865,0],[0,0.865],[0,0],[-11.173,0],[0,0],[0,0.865],[-0.865,0],[0,0]],"v":[[-209.145,-381.37],[-209.145,-400.741],[-181.854,-428.031],[-162.431,-428.031],[-160.866,-426.465],[-162.431,-424.899],[-181.854,-424.899],[-206.012,-400.741],[-206.012,-381.37],[-207.577,-379.803],[-209.143,-381.37]],"c":true}]},{"t":30.0000012219251,"s":[{"i":[[0,0],[0,0],[-12.881,0],[0,0],[0,-0.865],[0.865,0],[0,0],[0,-13.606],[0,0],[0.865,0],[0,0.865]],"o":[[0,0],[0,-15.62],[0,0],[0.865,0],[0,0.865],[0,0],[-11.173,0],[0,0],[0,0.865],[-0.865,0],[0,0]],"v":[[-73.228,-28.37],[-73.228,-47.741],[-45.938,-75.031],[-26.515,-75.031],[-24.949,-73.465],[-26.515,-71.9],[-45.938,-71.9],[-70.095,-47.741],[-70.095,-28.37],[-71.661,-26.803],[-73.227,-28.37]],"c":true}]}],"ix":2},"nm":"Path 1","mn":"ADBE Vector Shape - Group","hd":false},{"ind":1,"ty":"sh","ix":2,"ks":{"a":1,"k":[{"i":{"x":0,"y":1},"o":{"x":0.333,"y":0},"t":0,"s":[{"i":[[0,0],[0,0],[11.171,0],[0,0],[0,0.865],[-0.865,0],[0,0],[0,-15.62],[0,0],[0.865,0],[0,0.865]],"o":[[0,0],[0,-13.606],[0,0],[-0.865,0],[0,-0.865],[0,0],[12.882,0],[0,0],[0,0.865],[-0.866,0],[0,0]],"v":[[206.419,-381.044],[206.419,-400.417],[182.264,-424.575],[162.839,-424.575],[161.273,-426.141],[162.839,-427.707],[182.264,-427.707],[209.552,-400.417],[209.552,-381.045],[207.986,-379.479],[206.419,-381.045]],"c":true}]},{"t":30.0000012219251,"s":[{"i":[[0,0],[0,0],[11.171,0],[0,0],[0,0.865],[-0.865,0],[0,0],[0,-15.62],[0,0],[0.865,0],[0,0.865]],"o":[[0,0],[0,-13.606],[0,0],[-0.865,0],[0,-0.865],[0,0],[12.882,0],[0,0],[0,0.865],[-0.866,0],[0,0]],"v":[[70.095,-28.368],[70.095,-47.741],[45.94,-71.9],[26.515,-71.9],[24.949,-73.465],[26.515,-75.031],[45.94,-75.031],[73.228,-47.741],[73.228,-28.37],[71.662,-26.803],[70.095,-28.37]],"c":true}]}],"ix":2},"nm":"Path 2","mn":"ADBE Vector Shape - Group","hd":false},{"ind":2,"ty":"sh","ix":3,"ks":{"a":1,"k":[{"i":{"x":0,"y":1},"o":{"x":0.333,"y":0},"t":0,"s":[{"i":[[0,0],[0,15.616],[0,0],[-0.865,0],[0,-0.865],[0,0],[-11.173,0],[0,0],[0,-0.865],[0.865,0]],"o":[[-12.881,0],[0,0],[0,-0.865],[0.865,0],[0,0],[0,13.6],[0,0],[0.865,0],[0,0.865],[0,0]],"v":[[-182.938,427.031],[-210.228,399.745],[-210.228,380.368],[-208.662,378.803],[-207.096,380.368],[-207.096,399.741],[-182.939,423.897],[-163.515,423.897],[-161.949,425.462],[-163.515,427.027]],"c":true}]},{"t":30.0000012219251,"s":[{"i":[[0,0],[0,15.616],[0,0],[-0.865,0],[0,-0.865],[0,0],[-11.173,0],[0,0],[0,-0.865],[0.865,0]],"o":[[-12.881,0],[0,0],[0,-0.865],[0.865,0],[0,0],[0,13.6],[0,0],[0.865,0],[0,0.865],[0,0]],"v":[[-45.938,75.031],[-73.228,47.745],[-73.228,28.368],[-71.662,26.803],[-70.096,28.368],[-70.096,47.741],[-45.939,71.897],[-26.515,71.897],[-24.949,73.462],[-26.515,75.027]],"c":true}]}],"ix":2},"nm":"Path 3","mn":"ADBE Vector Shape - Group","hd":false},{"ind":3,"ty":"sh","ix":4,"ks":{"a":1,"k":[{"i":{"x":0,"y":1},"o":{"x":0.333,"y":0},"t":0,"s":[{"i":[[0,0],[0,0.865],[-0.865,0],[0,0],[0,13.603],[0,0],[-0.866,0],[0,-0.865],[0,0],[12.882,0]],"o":[[-0.865,0],[0,-0.864],[0,0],[11.171,0],[0,0],[0,-0.865],[0.865,0],[0,0],[0,15.618],[0,0]],"v":[[162.515,426.031],[160.949,424.466],[162.515,422.901],[181.94,422.901],[206.095,398.745],[206.095,379.368],[207.662,377.802],[209.228,379.368],[209.228,398.74],[181.94,426.027]],"c":true}]},{"t":30.0000012219251,"s":[{"i":[[0,0],[0,0.865],[-0.865,0],[0,0],[0,13.603],[0,0],[-0.866,0],[0,-0.865],[0,0],[12.882,0]],"o":[[-0.865,0],[0,-0.864],[0,0],[11.171,0],[0,0],[0,-0.865],[0.865,0],[0,0],[0,15.618],[0,0]],"v":[[26.515,75.031],[24.949,73.466],[26.515,71.901],[45.94,71.901],[70.095,47.745],[70.095,28.368],[71.662,26.803],[73.228,28.368],[73.228,47.741],[45.94,75.027]],"c":true}]}],"ix":2},"nm":"Path 4","mn":"ADBE Vector Shape - Group","hd":false},{"ty":"mm","mm":1,"nm":"Merge Paths 1","mn":"ADBE Vector Filter - Merge","hd":false},{"ty":"fl","c":{"a":0,"k":[1,1,1,1],"ix":4},"o":{"a":0,"k":100,"ix":5},"r":1,"bm":0,"nm":"Fill 1","mn":"ADBE Vector Graphic - Fill","hd":false},{"ty":"tr","p":{"a":0,"k":[73.478,75.281],"ix":2},"a":{"a":0,"k":[0,0],"ix":1},"s":{"a":0,"k":[100,100],"ix":3},"r":{"a":0,"k":0,"ix":6},"o":{"a":0,"k":100,"ix":7},"sk":{"a":0,"k":0,"ix":4},"sa":{"a":0,"k":0,"ix":5},"nm":"Transform"}],"nm":"Group 1","np":8,"cix":2,"bm":0,"ix":1,"mn":"ADBE Vector Group","hd":false}],"ip":0,"op":90.0000036657751,"st":0,"bm":0},{"ddd":0,"ind":2,"ty":4,"nm":"Ellipse Outlines","sr":1,"ks":{"o":{"a":0,"k":100,"ix":11},"r":{"a":0,"k":0,"ix":10},"p":{"a":0,"k":[193.262,421.71,0],"ix":2,"l":2},"a":{"a":0,"k":[58.067,39.899,0],"ix":1,"l":2},"s":{"a":0,"k":[100,100,100],"ix":6,"l":2}},"ao":0,"sy":[{"c":{"a":0,"k":[0,0,0,1],"ix":2},"o":{"a":0,"k":75,"ix":3},"a":{"a":0,"k":120,"ix":5},"s":{"a":0,"k":5,"ix":8},"d":{"a":0,"k":5,"ix":6},"ch":{"a":0,"k":0,"ix":7},"bm":{"a":0,"k":5,"ix":1},"no":{"a":0,"k":0,"ix":9},"lc":{"a":0,"k":1,"ix":10},"ty":1,"nm":"Drop Shadow"},{"c":{"a":0,"k":[0,0,0,1],"ix":2},"o":{"a":0,"k":75,"ix":3},"a":{"a":0,"k":120,"ix":5},"s":{"a":0,"k":5,"ix":8},"d":{"a":0,"k":5,"ix":6},"ch":{"a":0,"k":0,"ix":7},"bm":{"a":0,"k":5,"ix":1},"no":{"a":0,"k":0,"ix":9},"ty":2,"nm":"Inner Shadow"},{"c":{"a":0,"k":[1,1,0.745098039216,1],"ix":5},"o":{"a":0,"k":75,"ix":2},"s":{"a":0,"k":5,"ix":10},"r":{"a":0,"k":50,"ix":11},"ch":{"a":0,"k":0,"ix":9},"bm":{"a":0,"k":11,"ix":1},"no":{"a":0,"k":0,"ix":3},"j":{"a":0,"k":0,"ix":12},"ty":3,"nm":"Outer Glow"},{"c":{"a":0,"k":[1,1,0.745098039216,1],"ix":5},"o":{"a":0,"k":75,"ix":2},"s":{"a":0,"k":5,"ix":11},"r":{"a":0,"k":50,"ix":12},"sr":{"a":0,"k":1,"ix":9},"ch":{"a":0,"k":0,"ix":10},"bm":{"a":0,"k":11,"ix":1},"no":{"a":0,"k":0,"ix":3},"j":{"a":0,"k":0,"ix":13},"ty":4,"nm":"Inner Glow"},{"bs":{"a":0,"k":2,"ix":1},"bt":{"a":0,"k":1,"ix":2},"sr":{"a":0,"k":100,"ix":3},"bd":{"a":0,"k":1,"ix":4},"s":{"a":0,"k":5,"ix":5},"so":{"a":0,"k":75,"ix":15},"ga":{"a":0,"k":0,"ix":7},"a":{"a":0,"k":120,"ix":8},"ll":{"a":0,"k":30,"ix":9},"hm":{"a":0,"k":11,"ix":10},"hc":{"a":0,"k":[1,1,1,1],"ix":11},"ho":{"a":0,"k":75,"ix":12},"sm":{"a":0,"k":5,"ix":13},"sc":{"a":0,"k":[0,0,0,1],"ix":14},"ty":5,"nm":"Bevel and Emboss"},{"bm":{"a":0,"k":5,"ix":1},"c":{"a":0,"k":[0,0,0,1],"ix":2},"o":{"a":0,"k":50,"ix":3},"a":{"a":0,"k":19,"ix":4},"d":{"a":0,"k":11,"ix":5},"s":{"a":0,"k":14,"ix":6},"in":{"a":0,"k":1,"ix":7},"ty":6,"nm":"Satin"},{"bm":{"a":0,"k":1,"ix":1},"c":{"a":0,"k":[1,0,0,1],"ix":2},"so":{"a":0,"k":100,"ix":3},"ty":7,"nm":"Color Overlay"},{"bm":{"a":0,"k":1,"ix":1},"o":{"a":0,"k":100,"ix":2},"gf":{"a":0,"ix":3},"gs":{"a":0,"k":100,"ix":4},"a":{"a":0,"k":90,"ix":5},"gt":{"a":0,"k":1,"ix":6},"re":{"a":0,"k":0,"ix":7},"al":{"a":0,"k":1,"ix":8},"s":{"a":0,"k":100,"ix":9},"of":{"a":0,"k":[0,0],"ix":10},"ty":8,"nm":"Gradient Overlay"},{"c":{"a":0,"k":[1,0,0,1],"ix":2},"s":{"a":0,"k":3,"ix":3},"ty":0,"nm":"Stroke"}],"shapes":[{"ty":"gr","it":[{"ind":0,"ty":"sh","ix":1,"ks":{"a":0,"k":{"i":[[-1.911,0],[0,-1.91],[1.91,0],[0,1.911]],"o":[[1.91,0],[0,1.911],[-1.911,0],[0,-1.91]],"v":[[0,-3.46],[3.46,0],[0,3.46],[-3.46,0]],"c":true},"ix":2},"nm":"Path 1","mn":"ADBE Vector Shape - Group","hd":false},{"ty":"fl","c":{"a":0,"k":[1,1,1,1],"ix":4},"o":{"a":0,"k":100,"ix":5},"r":1,"bm":0,"nm":"Fill 1","mn":"ADBE Vector Graphic - Fill","hd":false},{"ty":"tr","p":{"a":0,"k":[109.25,37.16],"ix":2},"a":{"a":0,"k":[0,0],"ix":1},"s":{"a":1,"k":[{"i":{"x":[0.094,0.094],"y":[0.972,0.972]},"o":{"x":[0.333,0.333],"y":[0,0]},"t":58,"s":[0,0]},{"t":63.0000025660426,"s":[100,100]}],"ix":3},"r":{"a":0,"k":0,"ix":6},"o":{"a":0,"k":100,"ix":7},"sk":{"a":0,"k":0,"ix":4},"sa":{"a":0,"k":0,"ix":5},"nm":"Transform"}],"nm":"Group 1","np":4,"cix":2,"bm":0,"ix":1,"mn":"ADBE Vector Group","hd":false},{"ty":"gr","it":[{"ind":0,"ty":"sh","ix":1,"ks":{"a":0,"k":{"i":[[-1.434,0],[0,-1.433],[1.433,0],[0,1.433]],"o":[[1.433,0],[0,1.433],[-1.434,0],[0,-1.433]],"v":[[0,-2.595],[2.595,0],[0,2.595],[-2.595,0]],"c":true},"ix":2},"nm":"Path 1","mn":"ADBE Vector Shape - Group","hd":false},{"ty":"fl","c":{"a":0,"k":[1,1,1,1],"ix":4},"o":{"a":0,"k":100,"ix":5},"r":1,"bm":0,"nm":"Fill 1","mn":"ADBE Vector Graphic - Fill","hd":false},{"ty":"tr","p":{"a":0,"k":[41.485,2.845],"ix":2},"a":{"a":0,"k":[0,0],"ix":1},"s":{"a":1,"k":[{"i":{"x":[0.094,0.094],"y":[0.972,0.972]},"o":{"x":[0.333,0.333],"y":[0,0]},"t":56,"s":[0,0]},{"t":61.0000024845809,"s":[100,100]}],"ix":3},"r":{"a":0,"k":0,"ix":6},"o":{"a":0,"k":100,"ix":7},"sk":{"a":0,"k":0,"ix":4},"sa":{"a":0,"k":0,"ix":5},"nm":"Transform"}],"nm":"Group 2","np":4,"cix":2,"bm":0,"ix":2,"mn":"ADBE Vector Group","hd":false},{"ty":"gr","it":[{"ind":0,"ty":"sh","ix":1,"ks":{"a":0,"k":{"i":[[-1.433,0],[0,-1.433],[1.433,0],[0,1.433]],"o":[[1.433,0],[0,1.433],[-1.433,0],[0,-1.433]],"v":[[0,-2.595],[2.595,0],[0,2.595],[-2.595,0]],"c":true},"ix":2},"nm":"Path 1","mn":"ADBE Vector Shape - Group","hd":false},{"ty":"fl","c":{"a":0,"k":[1,1,1,1],"ix":4},"o":{"a":0,"k":100,"ix":5},"r":1,"bm":0,"nm":"Fill 1","mn":"ADBE Vector Graphic - Fill","hd":false},{"ty":"tr","p":{"a":0,"k":[2.845,18.993],"ix":2},"a":{"a":0,"k":[0,0],"ix":1},"s":{"a":1,"k":[{"i":{"x":[0.094,0.094],"y":[0.972,0.972]},"o":{"x":[0.333,0.333],"y":[0,0]},"t":54,"s":[0,0]},{"t":59.0000024031193,"s":[100,100]}],"ix":3},"r":{"a":0,"k":0,"ix":6},"o":{"a":0,"k":100,"ix":7},"sk":{"a":0,"k":0,"ix":4},"sa":{"a":0,"k":0,"ix":5},"nm":"Transform"}],"nm":"Group 3","np":4,"cix":2,"bm":0,"ix":3,"mn":"ADBE Vector Group","hd":false},{"ty":"gr","it":[{"ind":0,"ty":"sh","ix":1,"ks":{"a":0,"k":{"i":[[-1.434,0],[0,-1.434],[1.433,0],[0,1.433]],"o":[[1.433,0],[0,1.433],[-1.434,0],[0,-1.434]],"v":[[0,-2.595],[2.595,0],[0,2.595],[-2.595,0]],"c":true},"ix":2},"nm":"Path 1","mn":"ADBE Vector Shape - Group","hd":false},{"ty":"fl","c":{"a":0,"k":[1,1,1,1],"ix":4},"o":{"a":0,"k":100,"ix":5},"r":1,"bm":0,"nm":"Fill 1","mn":"ADBE Vector Graphic - Fill","hd":false},{"ty":"tr","p":{"a":0,"k":[15.821,30.816],"ix":2},"a":{"a":0,"k":[0,0],"ix":1},"s":{"a":1,"k":[{"i":{"x":[0.094,0.094],"y":[0.972,0.972]},"o":{"x":[0.333,0.333],"y":[0,0]},"t":56,"s":[0,0]},{"t":61.0000024845809,"s":[100,100]}],"ix":3},"r":{"a":0,"k":0,"ix":6},"o":{"a":0,"k":100,"ix":7},"sk":{"a":0,"k":0,"ix":4},"sa":{"a":0,"k":0,"ix":5},"nm":"Transform"}],"nm":"Group 4","np":4,"cix":2,"bm":0,"ix":4,"mn":"ADBE Vector Group","hd":false},{"ty":"gr","it":[{"ind":0,"ty":"sh","ix":1,"ks":{"a":0,"k":{"i":[[-1.433,0],[0,-1.434],[1.434,0],[0,1.433]],"o":[[1.434,0],[0,1.433],[-1.433,0],[0,-1.434]],"v":[[0,-2.595],[2.595,0],[0,2.595],[-2.595,0]],"c":true},"ix":2},"nm":"Path 1","mn":"ADBE Vector Shape - Group","hd":false},{"ty":"fl","c":{"a":0,"k":[1,1,1,1],"ix":4},"o":{"a":0,"k":100,"ix":5},"r":1,"bm":0,"nm":"Fill 1","mn":"ADBE Vector Graphic - Fill","hd":false},{"ty":"tr","p":{"a":0,"k":[74.647,30.816],"ix":2},"a":{"a":0,"k":[0,0],"ix":1},"s":{"a":1,"k":[{"i":{"x":[0.094,0.094],"y":[0.972,0.972]},"o":{"x":[0.333,0.333],"y":[0,0]},"t":56,"s":[0,0]},{"t":61.0000024845809,"s":[100,100]}],"ix":3},"r":{"a":0,"k":0,"ix":6},"o":{"a":0,"k":100,"ix":7},"sk":{"a":0,"k":0,"ix":4},"sa":{"a":0,"k":0,"ix":5},"nm":"Transform"}],"nm":"Group 5","np":4,"cix":2,"bm":0,"ix":5,"mn":"ADBE Vector Group","hd":false},{"ty":"gr","it":[{"ind":0,"ty":"sh","ix":1,"ks":{"a":0,"k":{"i":[[-1.752,0],[0,-1.752],[1.752,0],[0,1.752]],"o":[[1.752,0],[0,1.752],[-1.752,0],[0,-1.752]],"v":[[0,-3.172],[3.172,0],[0,3.172],[-3.172,0]],"c":true},"ix":2},"nm":"Path 1","mn":"ADBE Vector Shape - Group","hd":false},{"ty":"fl","c":{"a":0,"k":[1,1,1,1],"ix":4},"o":{"a":0,"k":100,"ix":5},"r":1,"bm":0,"nm":"Fill 1","mn":"ADBE Vector Graphic - Fill","hd":false},{"ty":"tr","p":{"a":0,"k":[92.237,64.266],"ix":2},"a":{"a":0,"k":[0,0],"ix":1},"s":{"a":1,"k":[{"i":{"x":[0.094,0.094],"y":[0.972,0.972]},"o":{"x":[0.333,0.333],"y":[0,0]},"t":58,"s":[0,0]},{"t":63.0000025660426,"s":[100,100]}],"ix":3},"r":{"a":0,"k":0,"ix":6},"o":{"a":0,"k":100,"ix":7},"sk":{"a":0,"k":0,"ix":4},"sa":{"a":0,"k":0,"ix":5},"nm":"Transform"}],"nm":"Group 6","np":4,"cix":2,"bm":0,"ix":6,"mn":"ADBE Vector Group","hd":false},{"ty":"gr","it":[{"ind":0,"ty":"sh","ix":1,"ks":{"a":0,"k":{"i":[[-0.955,0],[0,-0.956],[0.955,0],[0,0.956]],"o":[[0.955,0],[0,0.956],[-0.955,0],[0,-0.956]],"v":[[0,-1.73],[1.73,0],[0,1.73],[-1.73,0]],"c":true},"ix":2},"nm":"Path 1","mn":"ADBE Vector Shape - Group","hd":false},{"ty":"fl","c":{"a":0,"k":[1,1,1,1],"ix":4},"o":{"a":0,"k":100,"ix":5},"r":1,"bm":0,"nm":"Fill 1","mn":"ADBE Vector Graphic - Fill","hd":false},{"ty":"tr","p":{"a":0,"k":[100.6,38.89],"ix":2},"a":{"a":0,"k":[0,0],"ix":1},"s":{"a":1,"k":[{"i":{"x":[0.094,0.094],"y":[0.972,0.972]},"o":{"x":[0.333,0.333],"y":[0,0]},"t":54,"s":[0,0]},{"t":59.0000024031193,"s":[100,100]}],"ix":3},"r":{"a":0,"k":0,"ix":6},"o":{"a":0,"k":100,"ix":7},"sk":{"a":0,"k":0,"ix":4},"sa":{"a":0,"k":0,"ix":5},"nm":"Transform"}],"nm":"Group 7","np":4,"cix":2,"bm":0,"ix":7,"mn":"ADBE Vector Group","hd":false},{"ty":"gr","it":[{"ind":0,"ty":"sh","ix":1,"ks":{"a":0,"k":{"i":[[-1.433,0],[0,-1.433],[1.434,0],[0,1.433]],"o":[[1.434,0],[0,1.433],[-1.433,0],[0,-1.433]],"v":[[0,-2.595],[2.595,0],[0,2.595],[-2.595,0]],"c":true},"ix":2},"nm":"Path 1","mn":"ADBE Vector Shape - Group","hd":false},{"ty":"fl","c":{"a":0,"k":[1,1,1,1],"ix":4},"o":{"a":0,"k":100,"ix":5},"r":1,"bm":0,"nm":"Fill 1","mn":"ADBE Vector Graphic - Fill","hd":false},{"ty":"tr","p":{"a":0,"k":[38.025,21.588],"ix":2},"a":{"a":0,"k":[0,0],"ix":1},"s":{"a":1,"k":[{"i":{"x":[0.094,0.094],"y":[0.972,0.972]},"o":{"x":[0.333,0.333],"y":[0,0]},"t":54,"s":[0,0]},{"t":59.0000024031193,"s":[100,100]}],"ix":3},"r":{"a":0,"k":0,"ix":6},"o":{"a":0,"k":100,"ix":7},"sk":{"a":0,"k":0,"ix":4},"sa":{"a":0,"k":0,"ix":5},"nm":"Transform"}],"nm":"Group 8","np":4,"cix":2,"bm":0,"ix":8,"mn":"ADBE Vector Group","hd":false},{"ty":"gr","it":[{"ind":0,"ty":"sh","ix":1,"ks":{"a":0,"k":{"i":[[-1.433,0],[0,-1.434],[1.433,0],[0,1.432]],"o":[[1.433,0],[0,1.432],[-1.433,0],[0,-1.434]],"v":[[0,-2.595],[2.595,0.001],[0,2.595],[-2.595,0.001]],"c":true},"ix":2},"nm":"Path 1","mn":"ADBE Vector Shape - Group","hd":false},{"ty":"fl","c":{"a":0,"k":[1,1,1,1],"ix":4},"o":{"a":0,"k":100,"ix":5},"r":1,"bm":0,"nm":"Fill 1","mn":"ADBE Vector Graphic - Fill","hd":false},{"ty":"tr","p":{"a":0,"k":[6.305,54.173],"ix":2},"a":{"a":0,"k":[0,0],"ix":1},"s":{"a":1,"k":[{"i":{"x":[0.094,0.094],"y":[0.972,0.972]},"o":{"x":[0.333,0.333],"y":[0,0]},"t":54,"s":[0,0]},{"t":59.0000024031193,"s":[100,100]}],"ix":3},"r":{"a":0,"k":0,"ix":6},"o":{"a":0,"k":100,"ix":7},"sk":{"a":0,"k":0,"ix":4},"sa":{"a":0,"k":0,"ix":5},"nm":"Transform"}],"nm":"Group 9","np":4,"cix":2,"bm":0,"ix":9,"mn":"ADBE Vector Group","hd":false},{"ty":"gr","it":[{"ind":0,"ty":"sh","ix":1,"ks":{"a":0,"k":{"i":[[-1.434,0],[0,-1.434],[1.433,0],[0,1.432]],"o":[[1.433,0],[0,1.432],[-1.434,0],[0,-1.434]],"v":[[0.001,-2.595],[2.596,0],[0.001,2.595],[-2.596,0]],"c":true},"ix":2},"nm":"Path 1","mn":"ADBE Vector Shape - Group","hd":false},{"ty":"fl","c":{"a":0,"k":[1,1,1,1],"ix":4},"o":{"a":0,"k":100,"ix":5},"r":1,"bm":0,"nm":"Fill 1","mn":"ADBE Vector Graphic - Fill","hd":false},{"ty":"tr","p":{"a":0,"k":[113.288,75.224],"ix":2},"a":{"a":0,"k":[0,0],"ix":1},"s":{"a":1,"k":[{"i":{"x":[0.094,0.094],"y":[0.972,0.972]},"o":{"x":[0.333,0.333],"y":[0,0]},"t":56,"s":[0,0]},{"t":61.0000024845809,"s":[100,100]}],"ix":3},"r":{"a":0,"k":0,"ix":6},"o":{"a":0,"k":100,"ix":7},"sk":{"a":0,"k":0,"ix":4},"sa":{"a":0,"k":0,"ix":5},"nm":"Transform"}],"nm":"Group 10","np":4,"cix":2,"bm":0,"ix":10,"mn":"ADBE Vector Group","hd":false},{"ty":"gr","it":[{"ind":0,"ty":"sh","ix":1,"ks":{"a":0,"k":{"i":[[-2.389,0],[0,-2.388],[2.389,0],[0,2.389]],"o":[[2.389,0],[0,2.389],[-2.389,0],[0,-2.388]],"v":[[0,-4.325],[4.325,0],[0,4.325],[-4.325,0]],"c":true},"ix":2},"nm":"Path 1","mn":"ADBE Vector Shape - Group","hd":false},{"ty":"fl","c":{"a":0,"k":[1,1,1,1],"ix":4},"o":{"a":0,"k":100,"ix":5},"r":1,"bm":0,"nm":"Fill 1","mn":"ADBE Vector Graphic - Fill","hd":false},{"ty":"tr","p":{"a":0,"k":[15.821,75.224],"ix":2},"a":{"a":0,"k":[0,0],"ix":1},"s":{"a":1,"k":[{"i":{"x":[0.094,0.094],"y":[0.972,0.972]},"o":{"x":[0.333,0.333],"y":[0,0]},"t":58,"s":[0,0]},{"t":63.0000025660426,"s":[100,100]}],"ix":3},"r":{"a":0,"k":0,"ix":6},"o":{"a":0,"k":100,"ix":7},"sk":{"a":0,"k":0,"ix":4},"sa":{"a":0,"k":0,"ix":5},"nm":"Transform"}],"nm":"Group 11","np":4,"cix":2,"bm":0,"ix":11,"mn":"ADBE Vector Group","hd":false},{"ty":"gr","it":[{"ind":0,"ty":"sh","ix":1,"ks":{"a":0,"k":{"i":[[-2.389,0],[0,-2.388],[2.389,0],[0,2.389]],"o":[[2.389,0],[0,2.389],[-2.389,0],[0,-2.388]],"v":[[0,-4.325],[4.325,0],[0,4.325],[-4.325,0]],"c":true},"ix":2},"nm":"Path 1","mn":"ADBE Vector Shape - Group","hd":false},{"ty":"fl","c":{"a":0,"k":[1,1,1,1],"ix":4},"o":{"a":0,"k":100,"ix":5},"r":1,"bm":0,"nm":"Fill 1","mn":"ADBE Vector Graphic - Fill","hd":false},{"ty":"tr","p":{"a":0,"k":[60.517,75.224],"ix":2},"a":{"a":0,"k":[0,0],"ix":1},"s":{"a":1,"k":[{"i":{"x":[0.094,0.094],"y":[0.972,0.972]},"o":{"x":[0.333,0.333],"y":[0,0]},"t":58,"s":[0,0]},{"t":63.0000025660426,"s":[100,100]}],"ix":3},"r":{"a":0,"k":0,"ix":6},"o":{"a":0,"k":100,"ix":7},"sk":{"a":0,"k":0,"ix":4},"sa":{"a":0,"k":0,"ix":5},"nm":"Transform"}],"nm":"Group 12","np":4,"cix":2,"bm":0,"ix":12,"mn":"ADBE Vector Group","hd":false},{"ty":"gr","it":[{"ind":0,"ty":"sh","ix":1,"ks":{"a":0,"k":{"i":[[-2.389,0],[0,-2.388],[2.389,0],[0,2.389]],"o":[[2.389,0],[0,2.389],[-2.389,0],[0,-2.388]],"v":[[0,-4.325],[4.325,0],[0,4.325],[-4.325,0]],"c":true},"ix":2},"nm":"Path 1","mn":"ADBE Vector Shape - Group","hd":false},{"ty":"fl","c":{"a":0,"k":[1,1,1,1],"ix":4},"o":{"a":0,"k":100,"ix":5},"r":1,"bm":0,"nm":"Fill 1","mn":"ADBE Vector Graphic - Fill","hd":false},{"ty":"tr","p":{"a":0,"k":[11.495,7.17],"ix":2},"a":{"a":0,"k":[0,0],"ix":1},"s":{"a":1,"k":[{"i":{"x":[0.094,0.094],"y":[0.972,0.972]},"o":{"x":[0.333,0.333],"y":[0,0]},"t":58,"s":[0,0]},{"t":63.0000025660426,"s":[100,100]}],"ix":3},"r":{"a":0,"k":0,"ix":6},"o":{"a":0,"k":100,"ix":7},"sk":{"a":0,"k":0,"ix":4},"sa":{"a":0,"k":0,"ix":5},"nm":"Transform"}],"nm":"Group 13","np":4,"cix":2,"bm":0,"ix":13,"mn":"ADBE Vector Group","hd":false}],"ip":-6.00000024438501,"op":90.0000036657752,"st":-6.00000024438501,"bm":0},{"ddd":0,"ind":3,"ty":4,"nm":"Line Outlines","sr":1,"ks":{"o":{"a":0,"k":100,"ix":11},"r":{"a":0,"k":0,"ix":10},"p":{"a":0,"k":[183.483,417.986,0],"ix":2,"l":2},"a":{"a":0,"k":[67.897,52.203,0],"ix":1,"l":2},"s":{"a":0,"k":[100,100,100],"ix":6,"l":2}},"ao":0,"hasMask":true,"masksProperties":[{"inv":false,"mode":"a","pt":{"a":0,"k":{"i":[[0,0],[0,0],[0,0],[0,0]],"o":[[0,0],[0,0],[0,0],[0,0]],"v":[[140.414,-18.783],[-1.086,-18.783],[-1.086,116.717],[140.414,116.717]],"c":true},"ix":1},"o":{"a":0,"k":100,"ix":3},"x":{"a":0,"k":0,"ix":4},"nm":"Mask 1"}],"sy":[{"c":{"a":0,"k":[0,0,0,1],"ix":2},"o":{"a":0,"k":75,"ix":3},"a":{"a":0,"k":120,"ix":5},"s":{"a":0,"k":5,"ix":8},"d":{"a":0,"k":5,"ix":6},"ch":{"a":0,"k":0,"ix":7},"bm":{"a":0,"k":5,"ix":1},"no":{"a":0,"k":0,"ix":9},"lc":{"a":0,"k":1,"ix":10},"ty":1,"nm":"Drop Shadow"},{"c":{"a":0,"k":[0,0,0,1],"ix":2},"o":{"a":0,"k":75,"ix":3},"a":{"a":0,"k":120,"ix":5},"s":{"a":0,"k":5,"ix":8},"d":{"a":0,"k":5,"ix":6},"ch":{"a":0,"k":0,"ix":7},"bm":{"a":0,"k":5,"ix":1},"no":{"a":0,"k":0,"ix":9},"ty":2,"nm":"Inner Shadow"},{"c":{"a":0,"k":[1,1,0.745098039216,1],"ix":5},"o":{"a":0,"k":75,"ix":2},"s":{"a":0,"k":5,"ix":10},"r":{"a":0,"k":50,"ix":11},"ch":{"a":0,"k":0,"ix":9},"bm":{"a":0,"k":11,"ix":1},"no":{"a":0,"k":0,"ix":3},"j":{"a":0,"k":0,"ix":12},"ty":3,"nm":"Outer Glow"},{"c":{"a":0,"k":[1,1,0.745098039216,1],"ix":5},"o":{"a":0,"k":75,"ix":2},"s":{"a":0,"k":5,"ix":11},"r":{"a":0,"k":50,"ix":12},"sr":{"a":0,"k":1,"ix":9},"ch":{"a":0,"k":0,"ix":10},"bm":{"a":0,"k":11,"ix":1},"no":{"a":0,"k":0,"ix":3},"j":{"a":0,"k":0,"ix":13},"ty":4,"nm":"Inner Glow"},{"bs":{"a":0,"k":2,"ix":1},"bt":{"a":0,"k":1,"ix":2},"sr":{"a":0,"k":100,"ix":3},"bd":{"a":0,"k":1,"ix":4},"s":{"a":0,"k":5,"ix":5},"so":{"a":0,"k":75,"ix":15},"ga":{"a":0,"k":0,"ix":7},"a":{"a":0,"k":120,"ix":8},"ll":{"a":0,"k":30,"ix":9},"hm":{"a":0,"k":11,"ix":10},"hc":{"a":0,"k":[1,1,1,1],"ix":11},"ho":{"a":0,"k":75,"ix":12},"sm":{"a":0,"k":5,"ix":13},"sc":{"a":0,"k":[0,0,0,1],"ix":14},"ty":5,"nm":"Bevel and Emboss"},{"bm":{"a":0,"k":5,"ix":1},"c":{"a":0,"k":[0,0,0,1],"ix":2},"o":{"a":0,"k":50,"ix":3},"a":{"a":0,"k":19,"ix":4},"d":{"a":0,"k":11,"ix":5},"s":{"a":0,"k":14,"ix":6},"in":{"a":0,"k":1,"ix":7},"ty":6,"nm":"Satin"},{"bm":{"a":0,"k":1,"ix":1},"c":{"a":0,"k":[1,0,0,1],"ix":2},"so":{"a":0,"k":100,"ix":3},"ty":7,"nm":"Color Overlay"},{"bm":{"a":0,"k":1,"ix":1},"o":{"a":0,"k":100,"ix":2},"gf":{"a":0,"ix":3},"gs":{"a":0,"k":100,"ix":4},"a":{"a":0,"k":90,"ix":5},"gt":{"a":0,"k":1,"ix":6},"re":{"a":0,"k":0,"ix":7},"al":{"a":0,"k":1,"ix":8},"s":{"a":0,"k":100,"ix":9},"of":{"a":0,"k":[0,0],"ix":10},"ty":8,"nm":"Gradient Overlay"},{"c":{"a":0,"k":[1,0,0,1],"ix":2},"s":{"a":0,"k":3,"ix":3},"ty":0,"nm":"Stroke"}],"shapes":[{"ty":"gr","it":[{"ind":0,"ty":"sh","ix":1,"ks":{"a":0,"k":{"i":[[0,0],[-2.611,-1.498],[-3.387,-2.155],[-2.6,-1.809],[-0.026,-0.018],[0,0],[0,0],[0,0],[0,0],[0,0],[0,0],[0,0],[0,0],[0,0],[0,0],[0,0],[0,0],[0,0],[0,0],[0,0],[0,0],[0,0],[0,0],[0,0],[0,0],[0,0],[0,0],[0,0],[0,0],[0,0],[0,0],[0,0],[0,0],[0,0],[0,0],[0,0],[0,0],[0,0],[0,0],[0,0],[0,0],[0,0],[0,0],[0,0],[0,0],[0,0],[0,0],[0,0],[0,0],[0,0],[0,0],[0,0],[4.507,3.134],[2.729,1.737],[3.384,1.909],[2.936,1.457]],"o":[[2.689,1.35],[3.361,1.897],[2.709,1.728],[4.486,3.119],[0,0],[0,0],[0,0],[0,0],[0,0],[0,0],[0,0],[0,0],[0,0],[0,0],[0,0],[0,0],[0,0],[0,0],[0,0],[0,0],[0,0],[0,0],[0,0],[0,0],[0,0],[0,0],[0,0],[0,0],[0,0],[0,0],[0,0],[0,0],[0,0],[0,0],[0,0],[0,0],[0,0],[0,0],[0,0],[0,0],[0,0],[0,0],[0,0],[0,0],[0,0],[0,0],[0,0],[0,0],[0,0],[0,0],[0,0],[-0.024,-0.019],[-2.618,-1.821],[-3.409,-2.168],[-2.845,-1.632],[0,0]],"v":[[-71.664,-46.833],[-63.712,-42.561],[-53.542,-36.455],[-45.533,-31.127],[-38.433,-25.951],[-38.15,-25.726],[-11.901,-20.849],[22.432,6.48],[-14.744,-4],[-14.764,-3.928],[-39.727,-17.072],[-39.792,-16.95],[-40.072,-17.179],[-50.152,-4.887],[-49.949,-4.696],[-71.664,7.475],[-71.664,8.49],[-71.586,8.628],[-49.155,-3.945],[-37.181,7.362],[-46.384,29.578],[-71.605,29.578],[-71.605,30.622],[-46.342,30.622],[-46.344,29.844],[-38.172,50.381],[-38.735,50.381],[-71.181,38.191],[-71.548,39.167],[-41.703,50.381],[-71.664,50.381],[-71.664,51.842],[-37.815,51.842],[-36.516,52.33],[-36.333,51.842],[-33.865,51.842],[-33.865,51.841],[-36.464,50.721],[-44.84,29.669],[-35.865,8.003],[-14.197,-0.97],[8.25,8.815],[16.45,29.669],[7.821,50.981],[5.791,51.84],[61.765,51.84],[58.393,44.511],[63.63,35.184],[58.393,13.179],[22.293,-10.651],[-11.147,-22.196],[-37.524,-27.096],[-44.695,-32.326],[-52.754,-37.687],[-62.991,-43.833],[-71.664,-48.467]],"c":true},"ix":2},"nm":"Path 5","mn":"ADBE Vector Shape - Group","hd":false},{"ind":1,"ty":"sh","ix":2,"ks":{"a":0,"k":{"i":[[0,0],[0,0],[0,0],[0,0],[0,0],[0,0],[0,0],[0,0],[0,0],[0,0],[0,0],[0,0],[0,0]],"o":[[0,0],[0,0],[0,0],[0,0],[0,0],[0,0],[0,0],[0,0],[0,0],[0,0],[0,0],[0,0],[0,0]],"v":[[-9.076,-19.935],[21.642,-9.331],[57.109,14.078],[62.039,34.793],[40.889,39.493],[40.809,39.255],[10.053,49.357],[17.833,30.134],[18.234,30.331],[26.914,12.733],[49.492,14.797],[32.32,5.422],[24.035,6.422]],"c":true},"ix":2},"nm":"Path 6","mn":"ADBE Vector Shape - Group","hd":false},{"ind":2,"ty":"sh","ix":3,"ks":{"a":0,"k":{"i":[[0,0],[0,0],[0,0],[0,0],[0,0],[0,0],[0,0],[0,0],[0,0],[0,0],[0,0]],"o":[[0,0],[0,0],[0,0],[0,0],[0,0],[0,0],[0,0],[0,0],[0,0],[0,0],[0,0]],"v":[[-48.728,-4.978],[-39.762,-15.911],[-14.413,-2.564],[-14.292,-2.793],[22.323,7.53],[26.213,12.044],[26.115,11.995],[17.74,28.971],[9.39,7.716],[-14.183,-2.56],[-36.417,6.649]],"c":true},"ix":2},"nm":"Path 7","mn":"ADBE Vector Shape - Group","hd":false},{"ind":3,"ty":"sh","ix":4,"ks":{"a":0,"k":{"i":[[0,0],[0,0],[0,0],[0,0],[0,0],[0,0],[0,0]],"o":[[0,0],[0,0],[0,0],[0,0],[0,0],[0,0],[0,0]],"v":[[25.837,7.673],[32.038,6.926],[42.607,12.698],[42.602,12.697],[27.52,11.319],[24.879,8.25],[25.615,8.457]],"c":true},"ix":2},"nm":"Path 8","mn":"ADBE Vector Shape - Group","hd":false},{"ind":4,"ty":"sh","ix":5,"ks":{"a":0,"k":{"i":[[0,0],[0,0],[0,0],[0,0],[0,0],[0,0],[0,0],[0,0],[0,0],[0,0],[0,0]],"o":[[0,0],[0,0],[0,0],[0,0],[0,0],[0,0],[0,0],[0,0],[0,0],[0,0],[0,0]],"v":[[56.729,43.89],[41.787,40.363],[61.51,35.979],[56.758,44.446],[59.488,50.377],[9.64,50.377],[10.006,49.474],[10.302,50.375],[39.331,40.84],[39.331,40.856],[56.49,44.906]],"c":true},"ix":2},"nm":"Path 9","mn":"ADBE Vector Shape - Group","hd":false},{"ind":5,"ty":"sh","ix":6,"ks":{"a":0,"k":{"i":[[0,0],[-2.156,-1.455],[-2.725,-2.144],[-2.013,-1.8],[-0.016,-0.017],[0,0],[0,0],[0,0],[0,0],[3.422,3.062],[2.2,1.734],[2.864,1.909],[2.533,1.432]],"o":[[2.252,1.294],[2.831,1.885],[2.18,1.717],[3.442,3.079],[0,0],[0,0],[0,0],[0,0],[-0.081,-0.088],[-2.035,-1.821],[-2.753,-2.168],[-2.415,-1.629],[0,0]],"v":[[-71.664,-39.445],[-65.049,-35.32],[-56.676,-29.248],[-50.358,-23.948],[-44.977,-18.78],[-71.664,-18.78],[-71.664,-17.319],[-41.622,-17.319],[-43.91,-19.776],[-49.384,-25.037],[-55.772,-30.394],[-64.239,-36.535],[-71.664,-41.127]],"c":true},"ix":2},"nm":"Path 10","mn":"ADBE Vector Shape - Group","hd":false},{"ind":6,"ty":"sh","ix":7,"ks":{"a":0,"k":{"i":[[0,0],[0,0],[0,0],[0,0],[0,0],[0,0],[0,0],[0,0]],"o":[[0,0],[0,0],[0,0],[0,0],[0,0],[0,0],[0,0],[0,0]],"v":[[-32.263,11.23],[-39.971,29.63],[-31.61,48.649],[-14.161,55.439],[5.428,46.433],[11.641,29.631],[4.337,11.639],[-14.163,3.822]],"c":true},"ix":2},"nm":"Path 2","mn":"ADBE Vector Shape - Group","hd":false},{"ind":7,"ty":"sh","ix":8,"ks":{"a":0,"k":{"i":[[0,0],[0,0],[0,0],[0,0],[0,0],[0,0],[0,0],[0,0]],"o":[[0,0],[0,0],[0,0],[0,0],[0,0],[0,0],[0,0],[0,0]],"v":[[-30.516,47.506],[-38.381,29.617],[-31.148,12.355],[-14.171,5.405],[3.214,12.749],[10.079,29.658],[4.268,45.358],[-14.21,53.853]],"c":true},"ix":2},"nm":"Path 3","mn":"ADBE Vector Shape - Group","hd":false},{"ty":"gf","o":{"a":0,"k":100,"ix":10},"r":2,"bm":0,"g":{"p":3,"k":{"a":0,"k":[0,0.004,0.49,0.961,0.5,0.18,0.588,0.98,1,0.357,0.686,1],"ix":9}},"s":{"a":0,"k":[0,-73],"ix":5},"e":{"a":0,"k":[-3,68],"ix":6},"t":1,"nm":"Gradient Fill 1","mn":"ADBE Vector Graphic - G-Fill","hd":false},{"ty":"tr","p":{"a":1,"k":[{"i":{"x":0,"y":0.995},"o":{"x":0.333,"y":0},"t":30,"s":[-182.517,40.486],"to":[42.667,0],"ti":[-42.667,0]},{"t":60.0000024438501,"s":[73.483,40.486]}],"ix":2},"a":{"a":0,"k":[0,0],"ix":1},"s":{"a":0,"k":[100,100],"ix":3},"r":{"a":0,"k":0,"ix":6},"o":{"a":0,"k":100,"ix":7},"sk":{"a":0,"k":0,"ix":4},"sa":{"a":0,"k":0,"ix":5},"nm":"Transform"}],"nm":"Group 1","np":9,"cix":2,"bm":0,"ix":1,"mn":"ADBE Vector Group","hd":false}],"ip":0,"op":90.0000036657751,"st":0,"bm":0},{"ddd":0,"ind":4,"ty":4,"nm":"Atoms Outlines","sr":1,"ks":{"o":{"a":1,"k":[{"i":{"x":[0.833],"y":[0.833]},"o":{"x":[0.167],"y":[0.167]},"t":30,"s":[0]},{"t":60.0000024438501,"s":[100]}],"ix":11},"r":{"a":0,"k":0,"ix":10},"p":{"a":0,"k":[140.665,364.25,0],"ix":2,"l":2},"a":{"a":0,"k":[631.774,437.953,0],"ix":1,"l":2},"s":{"a":0,"k":[100,100,100],"ix":6,"l":2}},"ao":0,"sy":[{"c":{"a":0,"k":[0,0,0,1],"ix":2},"o":{"a":0,"k":75,"ix":3},"a":{"a":0,"k":120,"ix":5},"s":{"a":0,"k":5,"ix":8},"d":{"a":0,"k":5,"ix":6},"ch":{"a":0,"k":0,"ix":7},"bm":{"a":0,"k":5,"ix":1},"no":{"a":0,"k":0,"ix":9},"lc":{"a":0,"k":1,"ix":10},"ty":1,"nm":"Drop Shadow"},{"c":{"a":0,"k":[0,0,0,1],"ix":2},"o":{"a":0,"k":75,"ix":3},"a":{"a":0,"k":120,"ix":5},"s":{"a":0,"k":5,"ix":8},"d":{"a":0,"k":5,"ix":6},"ch":{"a":0,"k":0,"ix":7},"bm":{"a":0,"k":5,"ix":1},"no":{"a":0,"k":0,"ix":9},"ty":2,"nm":"Inner Shadow"},{"c":{"a":0,"k":[1,1,0.745098039216,1],"ix":5},"o":{"a":0,"k":75,"ix":2},"s":{"a":0,"k":5,"ix":10},"r":{"a":0,"k":50,"ix":11},"ch":{"a":0,"k":0,"ix":9},"bm":{"a":0,"k":11,"ix":1},"no":{"a":0,"k":0,"ix":3},"j":{"a":0,"k":0,"ix":12},"ty":3,"nm":"Outer Glow"},{"c":{"a":0,"k":[1,1,0.745098039216,1],"ix":5},"o":{"a":0,"k":75,"ix":2},"s":{"a":0,"k":5,"ix":11},"r":{"a":0,"k":50,"ix":12},"sr":{"a":0,"k":1,"ix":9},"ch":{"a":0,"k":0,"ix":10},"bm":{"a":0,"k":11,"ix":1},"no":{"a":0,"k":0,"ix":3},"j":{"a":0,"k":0,"ix":13},"ty":4,"nm":"Inner Glow"},{"bs":{"a":0,"k":2,"ix":1},"bt":{"a":0,"k":1,"ix":2},"sr":{"a":0,"k":100,"ix":3},"bd":{"a":0,"k":1,"ix":4},"s":{"a":0,"k":5,"ix":5},"so":{"a":0,"k":75,"ix":15},"ga":{"a":0,"k":0,"ix":7},"a":{"a":0,"k":120,"ix":8},"ll":{"a":0,"k":30,"ix":9},"hm":{"a":0,"k":11,"ix":10},"hc":{"a":0,"k":[1,1,1,1],"ix":11},"ho":{"a":0,"k":75,"ix":12},"sm":{"a":0,"k":5,"ix":13},"sc":{"a":0,"k":[0,0,0,1],"ix":14},"ty":5,"nm":"Bevel and Emboss"},{"bm":{"a":0,"k":5,"ix":1},"c":{"a":0,"k":[0,0,0,1],"ix":2},"o":{"a":0,"k":50,"ix":3},"a":{"a":0,"k":19,"ix":4},"d":{"a":0,"k":11,"ix":5},"s":{"a":0,"k":14,"ix":6},"in":{"a":0,"k":1,"ix":7},"ty":6,"nm":"Satin"},{"bm":{"a":0,"k":1,"ix":1},"c":{"a":0,"k":[1,0,0,1],"ix":2},"so":{"a":0,"k":100,"ix":3},"ty":7,"nm":"Color Overlay"},{"bm":{"a":0,"k":1,"ix":1},"o":{"a":0,"k":100,"ix":2},"gf":{"a":0,"ix":3},"gs":{"a":0,"k":100,"ix":4},"a":{"a":0,"k":90,"ix":5},"gt":{"a":0,"k":1,"ix":6},"re":{"a":0,"k":0,"ix":7},"al":{"a":0,"k":1,"ix":8},"s":{"a":0,"k":100,"ix":9},"of":{"a":0,"k":[0,0],"ix":10},"ty":8,"nm":"Gradient Overlay"},{"c":{"a":0,"k":[1,0,0,1],"ix":2},"s":{"a":0,"k":3,"ix":3},"ty":0,"nm":"Stroke"}],"shapes":[{"ty":"gr","it":[{"ind":0,"ty":"sh","ix":1,"ks":{"a":0,"k":{"i":[[0,0],[12.082,-0.021],[3.951,-2.296],[0,0],[0.085,0.192],[0,0],[0,0],[-1.219,0.001],[0,0],[-2.775,0.975],[0,0],[-0.017,-9.537],[0,0],[-2.065,-3.797]],"o":[[-3.398,-10.966],[-4.897,0.007],[0,0],[0,-0.21],[0,0],[0,0],[1.176,0.156],[0,0],[3.107,-0.005],[0,0],[-7.482,4.78],[0,0],[0.004,4.627],[0,0]],"v":[[420.023,233.84],[394.312,214.937],[380.878,218.566],[380.878,137.851],[380.75,137.242],[380.739,137.219],[458.683,5.25],[462.275,5.493],[462.325,5.493],[471.189,3.973],[543.63,165.511],[531.205,188.206],[531.205,188.21],[534.449,200.987]],"c":true},"ix":2},"nm":"Path 1","mn":"ADBE Vector Shape - Group","hd":false},{"ind":1,"ty":"sh","ix":2,"ks":{"a":0,"k":{"i":[[11.079,-17.756],[3.883,-3.155],[0,0],[0,0.039],[14.839,-0.025],[4.585,-8.211],[0,0],[0,0],[0,0],[-0.077,0.551],[0,0],[0,0],[0,0],[0,0],[0,0],[-0.714,-0.422],[-0.233,-0.012],[0,0],[-0.015,-8.643],[0,0],[-5.352,-4.902]],"o":[[-17.737,28.424],[0,0],[0,-0.04],[-0.025,-14.838],[-10.072,0.018],[0,0],[0,0],[0,0],[0.523,-0.188],[0,0],[0,0],[0,0],[0,0],[0,0],[-0.421,0.713],[0.215,0.126],[0,0],[-6.331,4.926],[0,0],[0.007,7.829],[-5.623,15.532]],"v":[[350.456,317.245],[298.049,374.306],[207.971,374.306],[207.974,374.188],[181.06,347.367],[157.639,361.157],[122.008,337.59],[97.207,297.789],[185.041,266.032],[186.016,264.83],[212.468,76.238],[266.907,10.68],[339.21,51.017],[377.37,137.022],[376.667,138.213],[377.196,140.268],[377.878,140.465],[377.878,220.591],[367.491,241.849],[367.491,241.852],[376.209,261.624]],"c":true},"ix":2},"nm":"Path 2","mn":"ADBE Vector Shape - Group","hd":false},{"ind":2,"ty":"sh","ix":3,"ks":{"a":0,"k":{"i":[[0,0],[0,0],[18.94,-0.03],[6.22,-6.25],[0,0],[0.391,0.038],[0,0],[-0.039,0.332],[0,0],[0,0],[-0.103,0],[0,0],[0,0],[-0.26,0.459],[0,0],[-3.104,0.003],[0,0],[-1.808,12.822],[0,0],[-0.253,0.177],[0,0],[-0.108,-0.063],[0,0],[-0.264,0],[0,0],[-14.428,0.011],[-0.014,0.001],[0.024,14.837],[2.989,4.322],[0,0],[-0.104,0.372],[0,0],[0,0],[-0.245,-0.245],[0,0],[0.038,-0.277],[0,0]],"o":[[0,0],[-0.145,-18.913],[-9.515,0.016],[0,0],[-0.252,-0.301],[0,0],[0.212,-0.226],[0,0],[0,0],[0.101,0.021],[0,0],[0,0],[0.527,-0.013],[0,0],[2.768,0.98],[0,0],[13.325,-0.023],[0,0],[0.308,0],[0,0],[0.088,0.086],[0,0],[0.228,0.132],[0,0],[0.631,14.275],[0.014,0],[14.837,-0.024],[-0.01,-5.654],[0,0],[0.343,-0.198],[0,0],[0,0],[0.03,0.372],[0,0],[-0.177,0.213],[0,0],[0,0]],"v":[[82.046,300.08],[-43.903,312.774],[-78.375,278.617],[-102.717,288.757],[-182.538,193.526],[-183.542,192.996],[-511.033,161.303],[-510.624,160.464],[-500.931,77.828],[-380.939,103.1],[-380.631,103.132],[-380.596,103.132],[-125.275,97.259],[-124.005,96.498],[-112.434,76.057],[-103.585,77.571],[-103.539,77.571],[-77.405,54.85],[-65.344,54.85],[-64.481,54.577],[-10.257,16.453],[-9.969,16.685],[18.668,33.296],[19.42,33.498],[50.166,33.498],[77,59.136],[77.044,59.135],[103.865,32.226],[99.107,17.01],[182.771,-31.383],[183.462,-32.275],[256.207,-69.06],[262.379,9.964],[262.823,10.903],[209.887,74.65],[209.556,75.4],[183.17,263.519]],"c":true},"ix":2},"nm":"Path 3","mn":"ADBE Vector Shape - Group","hd":false},{"ind":3,"ty":"sh","ix":4,"ks":{"a":0,"k":{"i":[[0,0],[0,0],[0,0]],"o":[[0,0],[0,0],[0,0]],"v":[[-186.474,195.727],[-184.442,195.923],[-149.027,238.177]],"c":true},"ix":2},"nm":"Path 4","mn":"ADBE Vector Shape - Group","hd":false},{"ind":4,"ty":"sh","ix":5,"ks":{"a":0,"k":{"i":[[0,0],[0.221,-7.528],[0,0],[0.689,2.656],[0,0],[0,0],[0,0],[0,0]],"o":[[-4.309,5.568],[0,0],[-0.029,-2.864],[0,0],[0,0],[0,0],[0,0],[0,0]],"v":[[-105.551,291.995],[-112.718,312.012],[-609.774,243.946],[-610.865,235.644],[-588.316,210.006],[-531.164,175.087],[-512.676,164.755],[-189.404,196.94]],"c":true},"ix":2},"nm":"Path 5","mn":"ADBE Vector Shape - Group","hd":false},{"ind":5,"ty":"sh","ix":6,"ks":{"a":0,"k":{"i":[[0,0],[0,0],[-0.035,0],[-0.259,0.176],[0,0],[-0.155,-0.113],[0,0],[-0.422,-0.308],[0,0],[0,0],[0.05,0],[0.236,-0.145],[0,0],[0,0],[0.113,-0.128],[0,0],[0,0],[0.077,-0.074],[0,0],[13.695,-0.023],[3.607,-1.29]],"o":[[0,0],[0.035,0.003],[0.29,0],[0,0],[0.102,0.163],[0,0],[-0.066,0.557],[0,0],[0,0],[-0.05,-0.006],[-0.275,0],[0,0],[0,0],[-0.149,0.083],[0,0],[0,0],[-0.091,0.056],[0,0],[-5.563,-11.57],[-4.049,0.007],[0,0]],"v":[[-659.542,195.458],[-657.05,180.328],[-656.945,180.341],[-656.102,180.081],[-504.249,76.653],[-503.862,77.066],[-513.603,160.114],[-512.994,161.496],[-513.318,161.678],[-514.236,161.586],[-514.385,161.578],[-515.167,161.798],[-532.676,172.495],[-584.852,201.654],[-585.247,201.974],[-590.268,207.682],[-590.622,207.899],[-590.876,208.095],[-613.149,229.409],[-644.246,209.884],[-655.784,211.892]],"c":true},"ix":2},"nm":"Path 6","mn":"ADBE Vector Shape - Group","hd":false},{"ind":6,"ty":"sh","ix":7,"ks":{"a":0,"k":{"i":[[0,0],[0,0],[-4.866,-0.002],[-1.823,0.489],[3.087,11.507],[0.115,0.356],[0,0],[-0.124,0.094],[-0.419,-0.254],[0,0],[-0.006,-3.619],[0,0],[-13.868,-0.795],[0,0],[0,0]],"o":[[0,0],[3.667,2.801],[1.888,0],[11.509,-3.088],[-0.098,-0.366],[0,0],[0.15,-0.053],[0.045,0.452],[0,0],[-1.311,3.144],[0,0],[0.013,14.071],[0,0],[0,0],[0,0]],"v":[[-645.991,113.193],[-622.891,10.9],[-609.797,15.333],[-604.206,14.597],[-588.958,-11.83],[-589.279,-12.913],[-576.654,-17.373],[-576.248,-17.602],[-575.539,-16.469],[-531.338,10.368],[-533.366,20.581],[-533.367,20.58],[-508.479,46.933],[-504.843,73.428],[-656.45,176.688]],"c":true},"ix":2},"nm":"Path 7","mn":"ADBE Vector Shape - Group","hd":false},{"ind":7,"ty":"sh","ix":8,"ks":{"a":0,"k":{"i":[[0,0],[0,0],[0,0],[0,0],[8.671,-0.531]],"o":[[0,0],[0,0],[0,0],[-3.807,-7.824],[0,0]],"v":[[-594.13,-87.118],[-566.695,-54.16],[-578.342,-19.967],[-590.408,-15.702],[-611.092,-27.779]],"c":true},"ix":2},"nm":"Path 8","mn":"ADBE Vector Shape - Group","hd":false},{"ind":8,"ty":"sh","ix":9,"ks":{"a":0,"k":{"i":[[0.466,0.684],[0.685,-0.466],[0,0],[0,0],[0.025,14.128],[7.989,4.539],[0,0],[0,0],[-0.167,0.007],[0,0],[0,0],[-0.015,-8.676],[0,0],[-8.763,-4.295],[0,0],[0,0],[0,0],[0.088,0.158],[0,0]],"o":[[-0.467,-0.684],[0,0],[0,0],[13.942,-0.764],[-0.017,-9.845],[0,0],[0,0],[0.16,0.044],[0,0],[0,0],[-6.446,4.834],[0,0],[0.01,10.418],[0,0],[0,0],[0,0],[-0.026,-0.184],[0,0],[0.686,-0.467]],"v":[[-499.621,71.686],[-501.705,71.29],[-502.074,71.542],[-505.45,46.94],[-480.474,20.489],[-493.879,-2.469],[-475.026,-28.545],[-375.426,-0.618],[-374.934,-0.565],[-147.985,-13.798],[-119.436,29.954],[-130.032,51.171],[-130.032,51.173],[-115.219,74.887],[-126.196,94.278],[-380.491,100.128],[-500.635,74.825],[-500.807,74.309],[-500.017,73.771]],"c":true},"ix":2},"nm":"Path 9","mn":"ADBE Vector Shape - Group","hd":false},{"ind":9,"ty":"sh","ix":10,"ks":{"a":0,"k":{"i":[[0,0],[-4.447,0.004],[0,0],[-2.791,1.575],[0,0],[-0.151,0],[-0.018,0.001],[0,0],[-9.575,0.008],[0,0],[0.019,10.664],[0.096,0.774],[0,0],[0,0],[0.264,-0.062],[0,0],[0.195,-0.409],[-0.196,-0.41],[0,0],[0,0],[0,0],[0.001,0.259],[14.606,-0.026],[3.907,-2.289],[0,0],[0.54,-0.021],[0,0],[0,0],[0.368,-0.51],[0,0],[3.677,-0.007],[4.514,-8.08],[0,0],[0.454,-0.246],[0,0],[0.016,0.198],[0.009,0.051],[0.008,0.033],[0.039,0.085],[0.007,0.014],[0.066,0.083],[0,0]],"o":[[3.264,2.524],[0,0],[3.433,-0.005],[0,0],[0.144,0.044],[0.018,0],[0,0],[1.522,9.143],[0,0],[10.665,-0.018],[-0.001,-0.8],[0,0],[0,0],[-0.25,-0.078],[0,0],[-0.442,0.104],[-0.197,0.41],[0,0],[0,0],[0,0],[0.007,-0.257],[-0.025,-14.605],[-4.854,0.008],[0,0],[-0.294,-0.451],[0,0],[0,0],[-0.603,-0.169],[0,0],[-3.184,-1.35],[-9.913,0.017],[0,0],[-0.473,-0.286],[0,0],[0.066,-0.195],[-0.003,-0.053],[-0.006,-0.034],[-0.023,-0.09],[-0.007,-0.015],[-0.046,-0.093],[0,0],[0,0]],"v":[[-577.065,-119.236],[-565.27,-115.2],[-565.239,-115.2],[-555.798,-117.691],[-364.722,-58.326],[-364.277,-58.259],[-364.222,-58.26],[-62.925,-69.287],[-43.899,-53.178],[-43.866,-53.178],[-24.59,-72.521],[-24.752,-74.878],[166.145,-110.548],[140.257,-61.184],[139.476,-61.217],[-26.849,-22.108],[-27.858,-21.296],[-27.858,-19.999],[-11.656,13.769],[-65.819,51.85],[-77.158,51.85],[-77.14,51.079],[-103.632,24.68],[-116.935,28.299],[-145.948,-16.165],[-147.292,-16.843],[-374.858,-3.575],[-475.224,-31.716],[-476.844,-31.15],[-496.603,-3.821],[-506.966,-5.91],[-530.018,7.66],[-573.983,-19.033],[-575.476,-19.062],[-563.581,-53.987],[-563.518,-54.582],[-563.526,-54.738],[-563.556,-54.837],[-563.641,-55.101],[-563.666,-55.143],[-563.829,-55.41],[-592.402,-91.329]],"c":true},"ix":2},"nm":"Path 10","mn":"ADBE Vector Shape - Group","hd":false},{"ind":10,"ty":"sh","ix":11,"ks":{"a":0,"k":{"i":[[0,0],[0,0],[-4.831,-2.513],[0,0],[0,0],[0,0.157],[0.599,1.858]],"o":[[0,0],[3.148,4.4],[0,0],[0,0],[0.003,-0.156],[-0.004,-2.058],[0,0]],"v":[[-473.962,-190.642],[-386.746,-231.861],[-374.61,-221.324],[-405.077,-160.411],[-545.983,-134.074],[-545.96,-134.539],[-546.895,-140.434]],"c":true},"ix":2},"nm":"Path 11","mn":"ADBE Vector Shape - Group","hd":false},{"ind":11,"ty":"sh","ix":12,"ks":{"a":0,"k":{"i":[[-8.994,-0.446],[0,0],[-0.428,-1.656],[0,0],[0.571,-0.505],[0.082,-0.235],[0,0],[0,0],[0.027,0.147],[0.075,0.136],[0,0],[-4.659,0.003],[0,0],[-2.305,16.745]],"o":[[0,0],[0.025,1.785],[0,0],[-0.56,-0.489],[-0.199,0.177],[0,0],[0,0],[0.015,-0.141],[-0.031,-0.161],[0,0],[4.054,1.675],[0,0],[17.385,-0.029],[50.664,0.489]],"v":[[-189.976,-242.508],[188.67,-218.015],[189.355,-212.839],[-91.893,-138.592],[-93.868,-138.591],[-94.284,-137.96],[-95.917,-137.529],[-401.781,-159.068],[-401.791,-159.499],[-401.957,-159.942],[-371.892,-220.053],[-358.737,-217.453],[-358.68,-217.453],[-324.645,-247.14]],"c":true},"ix":2},"nm":"Path 12","mn":"ADBE Vector Shape - Group","hd":false},{"ind":12,"ty":"sh","ix":13,"ks":{"a":0,"k":{"i":[[8.825,-0.015],[1.827,-0.577],[0,0],[0,0],[-7.06,-1.521],[0,0],[0.12,-0.228],[0,0],[0,0]],"o":[[-2.017,0.004],[0,0],[0,0],[2.702,6.54],[0,0],[-0.199,0.134],[0,0],[0,0],[-2.319,-8.082]],"v":[[-43.934,-91.798],[-49.722,-90.902],[-89.649,-136.081],[190.311,-209.989],[205.861,-196.993],[170.941,-119.293],[170.448,-118.752],[167.919,-113.932],[-25.353,-77.818]],"c":true},"ix":2},"nm":"Path 13","mn":"ADBE Vector Shape - Group","hd":false},{"ind":13,"ty":"sh","ix":14,"ks":{"a":0,"k":{"i":[[-0.819,4.407],[0,0],[-0.026,-0.046],[-0.5,-0.035],[0,0],[-0.035,0],[-0.125,0.033],[0,0],[0,0],[-0.014,-7.523],[0,-0.058],[0,0],[0,0]],"o":[[0,0],[0.021,0.047],[0.248,0.435],[0,0],[0.035,0.003],[0.129,0],[0,0],[0,0],[-6.273,3.199],[0,0.058],[0,0],[0,0],[3.267,-2.809]],"v":[[-546.299,-130.962],[-406.082,-157.171],[-406.023,-157.028],[-404.826,-156.275],[-95.88,-134.519],[-95.775,-134.515],[-95.392,-134.565],[-92.895,-135.224],[-52.65,-89.685],[-63.209,-72.453],[-63.201,-72.28],[-364.076,-61.267],[-552.699,-119.87]],"c":true},"ix":2},"nm":"Path 14","mn":"ADBE Vector Shape - Group","hd":false},{"ind":14,"ty":"sh","ix":15,"ks":{"a":0,"k":{"i":[[8.095,-0.013],[0.912,-13.99],[0,0],[0,0],[0,0],[0,0],[-0.732,-0.383],[-0.236,0],[-0.268,0.512],[0,0],[0,0],[0,0]],"o":[[-14.226,0.024],[0,0],[0,0],[0,0],[0,0],[-0.378,0.733],[0.222,0.116],[0.54,0],[0,0],[0,0],[0,0],[-4.935,-5.655]],"v":[[76.955,5.405],[50.2,30.498],[19.824,30.498],[-8.064,14.321],[-24.346,-19.615],[138.544,-57.916],[139.179,-55.898],[139.875,-55.726],[141.204,-56.53],[141.422,-56.947],[179.139,-32.748],[97.244,14.621]],"c":true},"ix":2},"nm":"Path 15","mn":"ADBE Vector Shape - Group","hd":false},{"ind":15,"ty":"sh","ix":16,"ks":{"a":0,"k":{"i":[[0,0],[-0.041,0.439],[0,0],[0.027,17.003],[19.011,-0.03],[2.222,-16.837],[0,0],[0.041,-0.002],[0,0],[0.003,2.603],[0.237,1.621],[0,0],[0,0],[0,0],[-0.01,-6.08],[0,0],[0,0],[-0.491,-1.923],[0,0],[0.215,-0.488],[0,0],[0.019,-0.135],[0,0],[0.129,0],[-0.025,-14.838],[0,0],[0,0],[-10.031,-3.881],[0,0],[0,0],[0,0],[0,0],[0,0],[-0.201,0.449],[0,0],[-0.518,0.001],[0,0],[0.019,12.056],[1.105,2.605]],"o":[[0.363,-0.253],[0,0],[16.201,-2.819],[-0.032,-19.011],[-17.449,0.029],[0,0],[-0.043,-0.002],[0,0],[0.544,-2.438],[-0.003,-1.686],[0,0],[0,0],[0,0],[-3.679,4.272],[0,0],[0,0],[0.002,2.075],[0,0],[-0.529,0.06],[0,0],[-0.056,0.126],[0,0],[-0.129,-0.002],[-14.837,0.026],[0,0],[0,0],[0.011,11.402],[0,0],[0,0],[0,0],[0,0],[0,0],[0.483,-0.09],[0,0],[0.508,0.035],[0,0],[12.056,-0.019],[-0.004,-3.007],[0,0]],"v":[[261.421,-248.308],[262.057,-249.399],[272.684,-362.808],[301.168,-396.765],[266.689,-431.132],[232.631,-401.255],[-3.854,-414.825],[-3.98,-414.827],[-174.835,-410.312],[-174.001,-417.886],[-174.371,-422.849],[-52.015,-471.805],[378.86,-471.805],[427.118,-433.685],[421.224,-417.774],[421.223,-417.774],[421.223,-417.769],[421.98,-411.756],[365.512,-405.363],[364.309,-404.478],[322.616,-310.047],[322.503,-309.654],[314.096,-251.063],[313.711,-251.073],[286.891,-224.159],[286.89,-224.159],[286.89,-224.157],[304.053,-199.145],[257.775,-73.214],[181.634,-34.711],[142.821,-59.613],[169.9,-111.25],[169.911,-111.252],[171.003,-112.112],[208.954,-196.558],[210.491,-196.5],[210.525,-196.5],[232.318,-218.363],[230.596,-226.839]],"c":true},"ix":2},"nm":"Path 16","mn":"ADBE Vector Shape - Group","hd":false},{"ind":16,"ty":"sh","ix":17,"ks":{"a":0,"k":{"i":[[-2.61,-1.267],[0,0],[1.914,-0.003],[4.839,-4.766],[0,0],[-0.621,9.684],[0,0]],"o":[[0,0],[-1.801,-0.378],[-7.328,0.013],[0,0],[8.198,-4.203],[0,0],[1.961,2.096]],"v":[[551.169,-242.432],[467.811,-47.666],[462.23,-48.241],[443.427,-40.512],[325.994,-200.289],[340.563,-222.462],[544.261,-247.533]],"c":true},"ix":2},"nm":"Path 17","mn":"ADBE Vector Shape - Group","hd":false},{"ind":17,"ty":"sh","ix":18,"ks":{"a":0,"k":{"i":[[-2.367,0.003],[0,0],[-2.92,1.094],[0,0],[-0.012,-6.407],[-11.574,-2.975],[0,0],[0,0],[0.284,0.158],[0,0],[0.463,-0.556],[0,0],[0,0],[0,0.006],[0,0],[-0.131,0.356],[0,0]],"o":[[0,0],[3.302,-0.006],[0,0],[-3.737,4.624],[0.01,12.503],[0,0],[0,0],[-0.132,-0.297],[0,0],[-0.631,-0.353],[0,0],[0,0],[-0.001,-0.007],[0,0],[0.339,-0.171],[0,0],[2.186,0.573]],"v":[[313.756,-197.339],[313.805,-197.339],[323.186,-199.043],[441.372,-38.243],[435.411,-21.327],[455.553,4.65],[379.244,133.849],[341.75,49.342],[341.109,48.641],[267.28,7.453],[265.395,7.805],[265.234,7.998],[259.102,-70.504],[259.099,-70.522],[259.656,-70.804],[260.387,-71.625],[306.909,-198.217]],"c":true},"ix":2},"nm":"Path 18","mn":"ADBE Vector Shape - Group","hd":false},{"ind":18,"ty":"sh","ix":19,"ks":{"a":0,"k":{"i":[[0,0],[3.399,-1.668],[0,0],[0.019,10.667],[10.675,3.54],[0,0],[-1.211,-0.204]],"o":[[-4.021,0.087],[0,0],[8.999,-4.354],[-0.02,-11.865],[0,0],[1.14,0.382],[0,0]],"v":[[557.478,161.31],[546.255,164.029],[473.963,2.826],[489.144,-21.421],[470.736,-46.874],[553.949,-241.303],[557.478,-240.42]],"c":true},"ix":2},"nm":"Path 19","mn":"ADBE Vector Shape - Group","hd":false},{"ind":19,"ty":"sh","ix":20,"ks":{"a":0,"k":{"i":[[13.691,1.217],[0,0],[-0.319,0.001],[0,0],[0.022,12.983],[12.983,-0.022],[-0.021,-12.982],[-2.595,-3.774],[0,0],[12.841,1.594],[0,0],[0,0],[0,0],[-10.281,0.01],[0,0],[0.022,13.446],[13.446,-0.022],[4.312,-3.913],[0,0],[0.338,0],[0,0],[0.177,-0.071],[0,0],[16.268,-0.027],[-0.03,-19.01],[0,0],[-18.994,0.016],[0,0],[-4.446,13.834],[0,0],[0,0],[-0.001,-0.54],[0,0],[0,0],[-18.995,0.018],[0,0],[-0.935,0.078],[0,0],[0,0],[7.968,-0.012],[1.321,-10.774],[0,0],[0.007,0],[50.727,0.501],[0.001,0.601],[19.01,-0.03],[-0.03,-19.01],[0,0],[-3.015,-5.108],[0,0],[0.066,-0.046],[0,0],[7.52,-0.011],[-0.017,-10.664],[0,0],[-3.232,-3.447],[0,0],[0.028,-0.152],[0.094,-0.327],[0,0],[0.347,-0.093],[-3.087,-11.508],[-2.413,-2.543],[0,0],[0,0],[-0.043,-0.189],[0,0],[-0.023,-13.884],[-18.995,0.015],[0,0],[-1.356,17.743],[0,0],[-18.342,0.016],[0,0],[-1.405,17.695],[0,0],[-0.116,0.042],[0,0],[0,0],[-0.18,-0.119],[0,0],[-0.007,-3.688],[-14.824,0.011],[0,0],[-1.523,13.371],[0,0],[-0.265,0.211],[-19.136,30.668],[-5.699,15.628],[-5.854,0.006],[0,0],[0.026,14.839],[0.308,1.622],[0,0],[-9.081,0.008],[0,0],[0.025,14.838]],"o":[[0,0],[0.316,0.012],[0,0],[12.983,-0.021],[-0.021,-12.982],[-12.982,0.021],[0.004,4.927],[0,0],[-0.618,-13.128],[0,0],[0,0],[0,0],[3.569,9.013],[0,0],[13.447,-0.022],[-0.023,-13.447],[-6.281,0.01],[0,0],[-0.265,-0.209],[0,0],[-0.191,0],[0,0],[-3.619,-15.163],[-19.011,0.03],[0,0],[0.016,18.994],[0,0],[15.314,-0.024],[0,0],[0,0],[-0.025,0.534],[0,0],[0,0],[0.018,18.994],[0,0],[0.955,-0.002],[0,0],[0,0],[-3.82,-6.371],[-11.134,0.018],[0,0],[-0.006,0],[-8.928,-0.448],[0.029,-0.594],[-0.031,-19.011],[-19.011,0.032],[0,0],[0.006,6.361],[0,0],[-0.073,0.035],[0,0],[-3.198,-6.269],[-10.664,0.017],[0,0],[0.005,5.096],[0,0],[-0.077,0.14],[-0.266,0.193],[0,0],[-0.348,0.075],[-11.509,3.087],[0.957,3.561],[0,0],[0,0],[-0.031,0.192],[0,0],[-11.831,5.463],[0.016,18.995],[0,0],[18.096,-0.032],[0,0],[1.025,18.088],[0,0],[18.063,-0.028],[0,0],[0.123,-0.012],[0,0],[0,0],[0.115,0.184],[0,0],[-1.34,3.202],[0.012,14.825],[0,0],[13.783,-0.025],[0,0],[0.339,0],[0.341,-0.271],[10.972,-17.585],[4.415,3.178],[0,0],[14.839,-0.024],[-0.003,-1.711],[0,0],[4.863,6.897],[0,0],[14.838,-0.024],[-0.023,-14.01]],"v":[[560.478,161.406],[560.478,-240.109],[561.43,-240.086],[561.469,-240.086],[584.937,-263.632],[561.391,-287.099],[537.923,-263.554],[542.047,-250.283],[340.592,-225.489],[317.097,-250.859],[325.443,-309.024],[366.706,-402.479],[422.929,-408.844],[445.57,-393.467],[445.611,-393.467],[469.919,-417.853],[445.532,-442.16],[429.218,-435.849],[380.31,-474.482],[379.38,-474.805],[-52.304,-474.805],[-52.861,-474.697],[-174.951,-425.848],[-208.479,-452.251],[-242.846,-417.774],[-242.846,-417.772],[-208.425,-383.408],[-208.368,-383.408],[-175.653,-407.29],[-3.965,-411.827],[232.362,-398.265],[232.324,-396.654],[232.32,-396.657],[232.32,-396.646],[266.747,-362.287],[266.801,-362.287],[269.634,-362.418],[259.135,-250.372],[229.22,-229.537],[210.456,-240.156],[188.833,-221.011],[-189.783,-245.502],[-189.887,-245.503],[-324.357,-250.138],[-324.314,-251.931],[-358.791,-286.298],[-393.158,-251.82],[-393.158,-251.819],[-388.399,-234.398],[-475.353,-193.303],[-475.563,-193.182],[-548.076,-143.264],[-565.301,-153.818],[-584.579,-134.477],[-584.579,-134.475],[-579.348,-121.312],[-595.512,-91.899],[-595.667,-91.459],[-596.235,-90.67],[-614.341,-27.33],[-615.385,-27.078],[-630.633,-0.651],[-625.447,8.602],[-648.934,112.618],[-662.55,195.261],[-662.532,195.839],[-658.597,213.046],[-678.61,244.363],[-644.188,278.728],[-644.129,278.728],[-609.877,246.961],[-112.684,315.045],[-78.321,347.463],[-78.266,347.463],[-44.017,315.8],[82.532,303.046],[82.891,302.965],[94.322,298.832],[119.634,339.453],[120.081,339.911],[156.312,363.875],[154.241,374.281],[181.105,401.102],[181.154,401.102],[207.794,377.306],[298.58,377.306],[299.513,376.98],[353.001,318.833],[378.671,263.622],[394.355,268.67],[394.402,268.67],[421.224,241.758],[420.744,236.754],[536.102,203.633],[558.073,215.028],[558.117,215.028],[584.938,188.116]],"c":true},"ix":2},"nm":"Path 20","mn":"ADBE Vector Shape - Group","hd":false},{"ind":20,"ty":"sh","ix":21,"ks":{"a":0,"k":{"i":[[0.74,0.372],[0,0],[0.391,-0.704],[0,0],[-0.724,-0.401],[-0.402,0.725],[0,0],[0,0],[-0.226,0],[-0.264,0.524]],"o":[[0,0],[-0.719,-0.36],[0,0],[-0.401,0.725],[0.725,0.402],[0,0],[0,0],[0.216,0.109],[0.549,0],[0.372,-0.741]],"v":[[179.298,257.987],[-129.858,102.513],[-131.844,103.126],[-181.202,192.158],[-180.617,194.197],[-178.577,193.613],[-129.919,105.841],[177.95,260.667],[178.623,260.827],[179.964,260.001]],"c":true},"ix":2},"nm":"Path 21","mn":"ADBE Vector Shape - Group","hd":false},{"ty":"mm","mm":1,"nm":"Merge Paths 1","mn":"ADBE Vector Filter - Merge","hd":false},{"ty":"mm","mm":4,"nm":"Merge Paths 2","mn":"ADBE Vector Filter - Merge","hd":false},{"ty":"tr","p":{"a":0,"k":[678.609,474.804],"ix":2},"a":{"a":0,"k":[0,0],"ix":1},"s":{"a":0,"k":[100,100],"ix":3},"r":{"a":0,"k":0,"ix":6},"o":{"a":0,"k":100,"ix":7},"sk":{"a":0,"k":0,"ix":4},"sa":{"a":0,"k":0,"ix":5},"nm":"Transform"}],"nm":"Group 1","np":23,"cix":2,"bm":0,"ix":1,"mn":"ADBE Vector Group","hd":false},{"ty":"fl","c":{"a":0,"k":[1,1,1,1],"ix":4},"o":{"a":0,"k":3,"ix":5},"r":1,"bm":0,"nm":"Fill 1","mn":"ADBE Vector Graphic - Fill","hd":false}],"ip":0,"op":90.0000036657751,"st":0,"bm":0},{"ddd":0,"ind":5,"ty":4,"nm":"Background Outlines","sr":1,"ks":{"o":{"a":1,"k":[{"i":{"x":[0.833],"y":[0.833]},"o":{"x":[0.167],"y":[0.167]},"t":0,"s":[0]},{"t":15.0000006109625,"s":[100]}],"ix":11},"r":{"a":0,"k":0,"ix":10},"p":{"a":0,"k":[187.5,406,0],"ix":2,"l":2},"a":{"a":0,"k":[187.75,406.25,0],"ix":1,"l":2},"s":{"a":0,"k":[100,100,100],"ix":6,"l":2}},"ao":0,"sy":[{"c":{"a":0,"k":[0,0,0,1],"ix":2},"o":{"a":0,"k":75,"ix":3},"a":{"a":0,"k":120,"ix":5},"s":{"a":0,"k":5,"ix":8},"d":{"a":0,"k":5,"ix":6},"ch":{"a":0,"k":0,"ix":7},"bm":{"a":0,"k":5,"ix":1},"no":{"a":0,"k":0,"ix":9},"lc":{"a":0,"k":1,"ix":10},"ty":1,"nm":"Drop Shadow"},{"c":{"a":0,"k":[0,0,0,1],"ix":2},"o":{"a":0,"k":75,"ix":3},"a":{"a":0,"k":120,"ix":5},"s":{"a":0,"k":5,"ix":8},"d":{"a":0,"k":5,"ix":6},"ch":{"a":0,"k":0,"ix":7},"bm":{"a":0,"k":5,"ix":1},"no":{"a":0,"k":0,"ix":9},"ty":2,"nm":"Inner Shadow"},{"c":{"a":0,"k":[1,1,0.745098039216,1],"ix":5},"o":{"a":0,"k":75,"ix":2},"s":{"a":0,"k":5,"ix":10},"r":{"a":0,"k":50,"ix":11},"ch":{"a":0,"k":0,"ix":9},"bm":{"a":0,"k":11,"ix":1},"no":{"a":0,"k":0,"ix":3},"j":{"a":0,"k":0,"ix":12},"ty":3,"nm":"Outer Glow"},{"c":{"a":0,"k":[1,1,0.745098039216,1],"ix":5},"o":{"a":0,"k":75,"ix":2},"s":{"a":0,"k":5,"ix":11},"r":{"a":0,"k":50,"ix":12},"sr":{"a":0,"k":1,"ix":9},"ch":{"a":0,"k":0,"ix":10},"bm":{"a":0,"k":11,"ix":1},"no":{"a":0,"k":0,"ix":3},"j":{"a":0,"k":0,"ix":13},"ty":4,"nm":"Inner Glow"},{"bs":{"a":0,"k":2,"ix":1},"bt":{"a":0,"k":1,"ix":2},"sr":{"a":0,"k":100,"ix":3},"bd":{"a":0,"k":1,"ix":4},"s":{"a":0,"k":5,"ix":5},"so":{"a":0,"k":75,"ix":15},"ga":{"a":0,"k":0,"ix":7},"a":{"a":0,"k":120,"ix":8},"ll":{"a":0,"k":30,"ix":9},"hm":{"a":0,"k":11,"ix":10},"hc":{"a":0,"k":[1,1,1,1],"ix":11},"ho":{"a":0,"k":75,"ix":12},"sm":{"a":0,"k":5,"ix":13},"sc":{"a":0,"k":[0,0,0,1],"ix":14},"ty":5,"nm":"Bevel and Emboss"},{"bm":{"a":0,"k":5,"ix":1},"c":{"a":0,"k":[0,0,0,1],"ix":2},"o":{"a":0,"k":50,"ix":3},"a":{"a":0,"k":19,"ix":4},"d":{"a":0,"k":11,"ix":5},"s":{"a":0,"k":14,"ix":6},"in":{"a":0,"k":1,"ix":7},"ty":6,"nm":"Satin"},{"bm":{"a":0,"k":1,"ix":1},"c":{"a":0,"k":[1,0,0,1],"ix":2},"so":{"a":0,"k":100,"ix":3},"ty":7,"nm":"Color Overlay"},{"bm":{"a":0,"k":1,"ix":1},"o":{"a":0,"k":100,"ix":2},"gf":{"a":0,"ix":3},"gs":{"a":0,"k":100,"ix":4},"a":{"a":0,"k":90,"ix":5},"gt":{"a":0,"k":1,"ix":6},"re":{"a":0,"k":0,"ix":7},"al":{"a":0,"k":1,"ix":8},"s":{"a":0,"k":100,"ix":9},"of":{"a":0,"k":[0,0],"ix":10},"ty":8,"nm":"Gradient Overlay"},{"c":{"a":0,"k":[1,0,0,1],"ix":2},"s":{"a":0,"k":3,"ix":3},"ty":0,"nm":"Stroke"}],"shapes":[{"ty":"gr","it":[{"ind":0,"ty":"sh","ix":1,"ks":{"a":0,"k":{"i":[[0,0],[0,0],[0,0],[0,0]],"o":[[0,0],[0,0],[0,0],[0,0]],"v":[[-187.5,406],[187.5,406],[187.5,-406],[-187.5,-406]],"c":true},"ix":2},"nm":"Path 1","mn":"ADBE Vector Shape - Group","hd":false},{"ty":"gf","o":{"a":0,"k":100,"ix":10},"r":1,"bm":0,"g":{"p":3,"k":{"a":0,"k":[0,0,0.365,0.616,0.5,0,0.184,0.339,1,0,0.004,0.063],"ix":9}},"s":{"a":0,"k":[0,-410],"ix":5},"e":{"a":0,"k":[324,200],"ix":6},"t":2,"h":{"a":0,"k":0,"ix":7},"a":{"a":0,"k":0,"ix":8},"nm":"Gradient Fill 1","mn":"ADBE Vector Graphic - G-Fill","hd":false},{"ty":"tr","p":{"a":0,"k":[187.75,406.25],"ix":2},"a":{"a":0,"k":[0,0],"ix":1},"s":{"a":0,"k":[100,100],"ix":3},"r":{"a":0,"k":0,"ix":6},"o":{"a":0,"k":100,"ix":7},"sk":{"a":0,"k":0,"ix":4},"sa":{"a":0,"k":0,"ix":5},"nm":"Transform"}],"nm":"Group 1","np":4,"cix":2,"bm":0,"ix":1,"mn":"ADBE Vector Group","hd":false}],"ip":0,"op":90.0000036657751,"st":0,"bm":0},{"ddd":0,"ind":6,"ty":1,"nm":"Dark Blue Solid 1","sr":1,"ks":{"o":{"a":0,"k":100,"ix":11},"r":{"a":0,"k":0,"ix":10},"p":{"a":0,"k":[187.5,406,0],"ix":2,"l":2},"a":{"a":0,"k":[187.5,406,0],"ix":1,"l":2},"s":{"a":0,"k":[100,100,100],"ix":6,"l":2}},"ao":0,"sy":[{"c":{"a":0,"k":[0,0,0,1],"ix":2},"o":{"a":0,"k":75,"ix":3},"a":{"a":0,"k":120,"ix":5},"s":{"a":0,"k":5,"ix":8},"d":{"a":0,"k":5,"ix":6},"ch":{"a":0,"k":0,"ix":7},"bm":{"a":0,"k":5,"ix":1},"no":{"a":0,"k":0,"ix":9},"lc":{"a":0,"k":1,"ix":10},"ty":1,"nm":"Drop Shadow"},{"c":{"a":0,"k":[0,0,0,1],"ix":2},"o":{"a":0,"k":75,"ix":3},"a":{"a":0,"k":120,"ix":5},"s":{"a":0,"k":5,"ix":8},"d":{"a":0,"k":5,"ix":6},"ch":{"a":0,"k":0,"ix":7},"bm":{"a":0,"k":5,"ix":1},"no":{"a":0,"k":0,"ix":9},"ty":2,"nm":"Inner Shadow"},{"c":{"a":0,"k":[1,1,0.745098039216,1],"ix":5},"o":{"a":0,"k":75,"ix":2},"s":{"a":0,"k":5,"ix":10},"r":{"a":0,"k":50,"ix":11},"ch":{"a":0,"k":0,"ix":9},"bm":{"a":0,"k":11,"ix":1},"no":{"a":0,"k":0,"ix":3},"j":{"a":0,"k":0,"ix":12},"ty":3,"nm":"Outer Glow"},{"c":{"a":0,"k":[1,1,0.745098039216,1],"ix":5},"o":{"a":0,"k":75,"ix":2},"s":{"a":0,"k":5,"ix":11},"r":{"a":0,"k":50,"ix":12},"sr":{"a":0,"k":1,"ix":9},"ch":{"a":0,"k":0,"ix":10},"bm":{"a":0,"k":11,"ix":1},"no":{"a":0,"k":0,"ix":3},"j":{"a":0,"k":0,"ix":13},"ty":4,"nm":"Inner Glow"},{"bs":{"a":0,"k":2,"ix":1},"bt":{"a":0,"k":1,"ix":2},"sr":{"a":0,"k":100,"ix":3},"bd":{"a":0,"k":1,"ix":4},"s":{"a":0,"k":5,"ix":5},"so":{"a":0,"k":75,"ix":15},"ga":{"a":0,"k":0,"ix":7},"a":{"a":0,"k":120,"ix":8},"ll":{"a":0,"k":30,"ix":9},"hm":{"a":0,"k":11,"ix":10},"hc":{"a":0,"k":[1,1,1,1],"ix":11},"ho":{"a":0,"k":75,"ix":12},"sm":{"a":0,"k":5,"ix":13},"sc":{"a":0,"k":[0,0,0,1],"ix":14},"ty":5,"nm":"Bevel and Emboss"},{"bm":{"a":0,"k":5,"ix":1},"c":{"a":0,"k":[0,0,0,1],"ix":2},"o":{"a":0,"k":50,"ix":3},"a":{"a":0,"k":19,"ix":4},"d":{"a":0,"k":11,"ix":5},"s":{"a":0,"k":14,"ix":6},"in":{"a":0,"k":1,"ix":7},"ty":6,"nm":"Satin"},{"bm":{"a":0,"k":1,"ix":1},"c":{"a":0,"k":[1,0,0,1],"ix":2},"so":{"a":0,"k":100,"ix":3},"ty":7,"nm":"Color Overlay"},{"bm":{"a":0,"k":1,"ix":1},"o":{"a":0,"k":100,"ix":2},"gf":{"a":0,"ix":3},"gs":{"a":0,"k":100,"ix":4},"a":{"a":0,"k":90,"ix":5},"gt":{"a":0,"k":1,"ix":6},"re":{"a":0,"k":0,"ix":7},"al":{"a":0,"k":1,"ix":8},"s":{"a":0,"k":100,"ix":9},"of":{"a":0,"k":[0,0],"ix":10},"ty":8,"nm":"Gradient Overlay"},{"c":{"a":0,"k":[1,0,0,1],"ix":2},"s":{"a":0,"k":3,"ix":3},"ty":0,"nm":"Stroke"}],"sw":375,"sh":812,"sc":"#000110","ip":0,"op":90.0000036657751,"st":0,"bm":0}],"markers":[]}